<?xml version="1.0"?>
<OSCOutputGroup>
  <oscMessage>/wek/outputs</oscMessage>
  <hostName>localhost</hostName>
  <outputPort>12001</outputPort>
  <outputs class="linked-list">
    <wekimini.osc.OSCClassificationOutput>
      <name>OnOff</name>
      <numClasses>2</numClasses>
      <isSendingDistribution>false</isSendingDistribution>
    </wekimini.osc.OSCClassificationOutput>
    <wekimini.osc.OSCNumericOutput>
      <name>CutoffFreq</name>
      <min>0.0</min>
      <max>1.0</max>
      <outputType>REAL</outputType>
      <limitType>SOFT</limitType>
      <trainingDataLimitRestriction>DONT_ENFORCE_LIMITS</trainingDataLimitRestriction>
      <trainingDataIntegerRestriction>DONT_ENFORCE_INTEGER</trainingDataIntegerRestriction>
    </wekimini.osc.OSCNumericOutput>
    <wekimini.osc.OSCNumericOutput>
      <name>Gain</name>
      <min>0.0</min>
      <max>1.0</max>
      <outputType>REAL</outputType>
      <limitType>SOFT</limitType>
      <trainingDataLimitRestriction>DONT_ENFORCE_LIMITS</trainingDataLimitRestriction>
      <trainingDataIntegerRestriction>DONT_ENFORCE_INTEGER</trainingDataIntegerRestriction>
    </wekimini.osc.OSCNumericOutput>
    <wekimini.osc.OSCNumericOutput>
      <name>Q</name>
      <min>0.0</min>
      <max>1.0</max>
      <outputType>REAL</outputType>
      <limitType>SOFT</limitType>
      <trainingDataLimitRestriction>DONT_ENFORCE_LIMITS</trainingDataLimitRestriction>
      <trainingDataIntegerRestriction>DONT_ENFORCE_INTEGER</trainingDataIntegerRestriction>
    </wekimini.osc.OSCNumericOutput>
    <wekimini.osc.OSCNumericOutput>
      <name>Vol</name>
      <min>0.0</min>
      <max>1.0</max>
      <outputType>REAL</outputType>
      <limitType>SOFT</limitType>
      <trainingDataLimitRestriction>DONT_ENFORCE_LIMITS</trainingDataLimitRestriction>
      <trainingDataIntegerRestriction>DONT_ENFORCE_INTEGER</trainingDataIntegerRestriction>
    </wekimini.osc.OSCNumericOutput>
  </outputs>
</OSCOutputGroup>